tensorrt_bindings/__init__.py
tensorrt_bindings/tensorrt.so
tensorrt_bindings/plugin/__init__.py
tensorrt_bindings/plugin/_autotune.py
tensorrt_bindings/plugin/_export.py
tensorrt_bindings/plugin/_lib.py
tensorrt_bindings/plugin/_plugin_class.py
tensorrt_bindings/plugin/_tensor.py
tensorrt_bindings/plugin/_top_level.py
tensorrt_bindings/plugin/_utils.py
tensorrt_bindings/plugin/_validate.py
tensorrt_cu13_bindings-10.15.1.29.dist-info/LICENSE.txt
tensorrt_cu13_bindings-10.15.1.29.dist-info/METADATA
tensorrt_cu13_bindings-10.15.1.29.dist-info/WHEEL
tensorrt_cu13_bindings-10.15.1.29.dist-info/top_level.txt
tensorrt_cu13_bindings-10.15.1.29.dist-info/zip-safe
tensorrt_cu13_bindings-10.15.1.29.dist-info/RECORD
